dag2langgraph/__init__.py
dag2langgraph/cli.py
dag2langgraph/converter.py
dag2langgraph-0.1.1.dist-info/LICENSE
dag2langgraph-0.1.1.dist-info/METADATA
dag2langgraph-0.1.1.dist-info/WHEEL
dag2langgraph-0.1.1.dist-info/entry_points.txt
dag2langgraph-0.1.1.dist-info/RECORD
