Metadata-Version: 2.1
Name: dag2langgraph
Version: 0.1.1
Summary: Converts a Directed Acyclic Graph (DAG) JSON to LangGraph JSON format.
License: MIT
Author: Ron Vergis
Author-email: ron@vergis.io
Requires-Python: >=3.8,<4.0
Classifier: License :: OSI Approved :: MIT License
Classifier: Programming Language :: Python :: 3
Classifier: Programming Language :: Python :: 3.8
Classifier: Programming Language :: Python :: 3.9
Classifier: Programming Language :: Python :: 3.10
Classifier: Programming Language :: Python :: 3.11
Classifier: Programming Language :: Python :: 3.12
